MANIFEST.in
README.md
setup.py
tests/extractors/__init__.py
tests/extractors/test_base.py
tests/extractors/test_csv.py
tests/extractors/test_excel.py
tests/extractors/data/person.csv
tests/extractors/data/person.xlsx
yu/__init__.py
yu/argparseutils.py
yu/formula.py
yu/utils.py
yu/validators.py
yu.egg-info/PKG-INFO
yu.egg-info/SOURCES.txt
yu.egg-info/dependency_links.txt
yu.egg-info/top_level.txt
yu/extractors/__init__.py
yu/extractors/base.py
yu/extractors/csv.py
yu/extractors/excel.py