Metadata-Version: 1.1
Name: yu
Version: 0.5.0
Summary: pYthon Utilities.
Home-page: https://github.com/huyx/yu
Author: UNKNOWN
Author-email: UNKNOWN
License: UNKNOWN
Platform: UNKNOWN
Classifier: Development Status :: 3 - Alpha
Classifier: Operating System :: OS Independent
Classifier: Programming Language :: Python :: 3.6
Classifier: Topic :: Utilities
